Workbook

Sheet TERRA
A1: 請求ルール（2026-05-19更新）
A2: ■ TERRA請求ルール ・プロパー（GL/FP経由以外）: 15,000円/人（税別） ・プロパー（GL/FP経由稼働）: 請求なし ・BP稼働: 粗利×80%請求 ・TERRA折半（旧:松野折半）: 粗利×50%請求 ・岡本折半: 粗利×80%請求、岡本へ半分払い出し
A3: 最終更新: | B3: =TODAY()
A4: 担当 | B4: 区分 (P/BP) | C4: ステータス | D4: 氏名 | E4: 参画時期 | F4: 期間 | G4: 案件/上位会社 | H4: 単価(案件) | I4: 支払 サイト | J4: 勤怠表フロー | K4: 更新サイクル | L4: 業務内容 | M4: 仕入先(所属) | N4: 仕入単価 | O4: 粗利 | P4: TERRA 請求額 | Q4: 岡本 払出 | R4: 実入り | S4: 備考
B5: P | C5: 稼働中 | D5: 仲山雄輝 | E5: 2023/12 | F5: 長期 | G5: スウェル | H5: 370000 | I5: 45 | J5: 上位からくる | K5: 3か月更新 | L5: ヘルプデスク | M5: TERRA | O5: =H4 | P5: 15000 | R5: =P4
B6: P | C6: 稼働中 | D6: 吉田創志 | E6: 2024/3 | F6: 長期 | G6: Technocrats Japan | H6: 430000 | I6: 50 | J6: 吉岡さんから送る | K6: 3か月更新 | L6: インフラ運用監視 | M6: TERRA | O6: =H5 | P6: 15000 | R6: =P5
B7: P | C7: 稼働中 | D7: 蒲池佑萌 | E7: 2024/3 | F7: 長期 | G7: シートス | H7: 400000 | I7: 45 | J7: 上位からくる | K7: 3か月更新 | L7: ヘルプデスク | M7: TERRA | O7: =H6 | P7: 15000 | R7: =P6
B8: P | C8: 稼働中 | D8: 大野稔貴 | E8: 2024/4 | F8: 長期 | G8: ブライトウェイ | H8: 320000 | I8: 55 | J8: 上位からくる | K8: 3か月更新 | L8: 調整業務 | M8: TERRA | O8: =H7 | P8: 15000 | R8: =P7
B9: P | C9: 稼働中 | D9: 白須雄太 | E9: 2024/5 | F9: 長期 | G9: リブートテック | H9: 270000 | I9: 45 | J9: 上位からくる | K9: 長期 | L9: キッティング事務 | M9: TERRA | O9: =H8 | P9: 15000 | R9: =P8
B10: P | C10: 稼働中 | D10: 沼田航陽 | E10: 2024/6 | F10: 長期 | G10: アイゼンソリューション | H10: 360000 | I10: 55 | J10: 吉岡さんから送る | K10: 長期 | L10: 運用監視 | M10: TERRA | O10: =H9 | P10: 15000 | R10: =P9
B11: P | C11: 稼働中 | D11: 魚谷 | E11: 2025/4 | F11: 4月終了 | G11: スリーケーシー | H11: 400000 | I11: 55 | J11: 平本さんから送る | K11: 長期 | M11: TERRA | O11: =H10 | P11: 15000 | R11: =P10
B12: P | C12: 5月末終了 | D12: 片山 | E12: 2025/4 | F12: 5月末終了 | G12: タレントギア | H12: 570000 | I12: 30 | J12: ※松野から送る | K12: 長期 | M12: TERRA | O12: =H11 | P12: 15000 | R12: =P11
B13: P | C13: 稼働中 | D13: 赤木 | E13: 2025/7 | F13: 長期 | G13: SPPS | H13: 400000 | I13: 40 | J13: 上位からくる | K13: 長期 | L13: テスト | M13: TERRA | O13: =H12 | P13: 15000 | R13: =P12
B14: P | C14: 稼働中 | D14: 坪井 | E14: 2025/7 | F14: 長期 | G14: スウェル | H14: 380000 | I14: 50 | J14: 上位からくる | K14: 長期 | M14: TERRA | O14: =H13 | P14: 15000 | R14: =P13
B15: P | C15: 稼働中 | D15: 中村 | E15: 2025/8 | F15: 長期 | G15: SPJ | H15: 450000 | I15: 50 | J15: ※松野から送る | K15: 長期 | M15: TERRA | O15: =H14 | P15: 15000 | R15: =P14
B16: P | C16: 稼働中 | D16: 日比野 | E16: 2025/9 | F16: 長期 | G16: SPPS | H16: 400000 | I16: 40 | J16: 上位からくる | K16: 長期 | M16: TERRA | O16: =H15 | P16: 15000 | R16: =P15
A17: TERRA折半 | B17: BP | C17: 稼働中 | D17: 大本 | E17: 2025/9 | F17: 5月末終了 | G17: （確認中） | H17: 330000 | I17: 35 | J17: 所属からメール | K17: 長期 | N17: 300000 | O17: =H16-N16 | P17: =O16*0.8 | R17: =P16*0.5
A18: TERRA折半 | B18: BP | C18: 稼働中 | D18: 森 | E18: 2025/9 | F18: 長期 | G18: （確認中） | H18: 380000 | I18: 40 | J18: 所属からメール | K18: 長期 | N18: 320000 | O18: =H17-N17 | P18: =O17*0.8 | R18: =P17*0.5
B19: P | C19: 稼働中 | D19: 永野 | E19: 2025/10 | F19: 長期 | G19: （確認中） | H19: 680000 | I19: 45 | J19: 上位からくる | K19: 長期 | M19: TERRA | O19: =H18 | P19: 15000 | R19: =P18
B20: P | C20: 稼働中 | D20: 安江 | E20: 2025/10 | F20: 長期 | G20: （確認中） | H20: 480000 | I20: 45 | J20: 上位からくる | K20: 長期 | M20: TERRA | O20: =H19 | P20: 15000 | R20: =P19
B21: P | C21: 稼働中 | D21: 相川 | E21: 2025/10 | F21: 長期 | G21: SPPS | H21: 400000 | I21: 40 | J21: 上位からくる | K21: 長期 | M21: TERRA | O21: =H20 | P21: 15000 | R21: =P20
A22: TERRA折半 | B22: BP | C22: 稼働中 | D22: 芹澤 | E22: 2025/12 | F22: 長期 | G22: （確認中） | H22: 590000 | I22: 40 | J22: 平本さんから送る | K22: 長期 | N22: 500000 | O22: =H21-N21 | P22: =O21*0.8 | R22: =P21*0.5
B23: P | C23: 稼働中 | D23: 富永 | E23: 2026/1 | F23: 長期 | G23: SPPS | H23: 360000 | I23: 40 | J23: 上位からくる | K23: 長期 | M23: TERRA | O23: =H22 | P23: 15000 | R23: =P22
A24: 岡本 | B24: P | C24: 稼働中 | D24: 天野 | E24: 2026/1 | F24: 長期 | G24: comvace | H24: 490000 | I24: 50 | J24: 吉岡さんから送る | K24: 長期 | O24: =H23 | P24: 15000 | Q24: 9000 | R24: =P23-Q23
A25: 岡本 | B25: P | C25: 稼働中 | D25: 岩瀬 | E25: 2026/3 | F25: 長期 | G25: （確認中） | H25: 500000 | I25: 50 | K25: 長期 | O25: =H24 | P25: 15000 | Q25: 9000 | R25: =P24-Q24
A26: 岡本 | B26: P | C26: 稼働中 | D26: 加藤(T) | E26: 2026/3 | F26: 長期 | G26: （確認中） | H26: 380000 | I26: 45 | K26: 長期 | O26: =H25 | P26: 15000 | Q26: 9000 | R26: =P25-Q25
B27: P | C27: 稼働中 | D27: 山内清 | E27: 2024/10 | F27: 長期 | G27: スウェル（GL経由） | H27: 370000 | I27: 45 | J27: 上位からくる | K27: 3か月更新 | L27: 保守 | M27: TERRA | O27: =H26 | P27: 請求なし | S27: GL契約シートも参照
B28: P | C28: 稼働中 | D28: 田中みさ | E28: 2025/1 | F28: 長期 | G28: 相馬さん（GL/FT経由） | H28: 400000 | I28: 55 | J28: 上位からくる | K28: 3か月更新 | L28: システム保守 | M28: TERRA | O28: =H27 | P28: 請求なし | S28: 岡本折半
A29: 岡本折半 | B29: BP | C29: 稼働中 | D29: 佐々木 | E29: 2026/4 | F29: 長期 | G29: スウェル | H29: 610000 | I29: 45 | J29: 上位からくる | K29: 単月更新 | L29: Java開発 | N29: 560000 | O29: =H28-N28 | P29: =O28*0.8 | Q29: =P28*0.5 | R29: =P28-Q28 | S29: 岡本折半
B30: P | C30: 稼働中 | D30: 木村勇太 | E30: 2025/10 | F30: 長期 | G30: グレイスライン経由 | H30: 600000 | I30: 45 | J30: 上位からくる | K30: 単月更新 | L30: Java開発 | M30: TERRA | O30: =H29 | P30: 請求なし
B31: P | C31: 5月末終了 | D31: 原 | E31: 2026/3 | F31: 5月末終了 | G31: （調整中） | M31: TERRA | P31: 請求なし
B32: P | C32: 入場前 | D32: 川崎(新) | E32: 2026/4 | F32: 長期 | G32: （調整中） | M32: TERRA | P32: 請求なし
B33: P | C33: 入場前 | D33: 橋詰(新) | E33: 2026/4 | F33: 長期 | G33: （調整中） | H33: 450000 | I33: 45 | O33: =H32
B34: P | C34: 入場前 | D34: 佐々木(入) | E34: 2026/4 | F34: 長期 | G34: スウェル | H34: 610000 | I34: 45 | J34: 上位からくる | K34: 単月更新 | L34: Java開発 | M34: TERRA | O34: =H33
A35: TERRA折半 | B35: BP | C35: 入場前 | D35: 小山内 | E35: 2026/4 | F35: 長期 | G35: （調整中） | H35: 600000 | I35: 45 | K35: 単月更新 | N35: 540000 | O35: =H34-N34 | P35: =O34*0.8 | R35: =P34*0.5
A36: 小坂折半 | B36: BP | C36: 入場前 | D36: 吉田祥平 | E36: 2026/6 | F36: 長期 | G36: 省庁ネットワーク/ICT運用 | H36: 700000 | I36: 45 | J36: 所属からメール | K36: 単月更新 | L36: 省庁NW/ICT運用 | N36: 650000 | O36: 50000 | P36: 40000 | R36: 40000 | S36: FP→TERRA→所属。FP単価75万、FP-TR70万、TR-所属65万。TERRA粗利5万×80%=4万。FP粗利5万×48%(小坂折半)=2.4万。精算140-180h中間割。松野担当。
A37: 稼働中合計 | H37: =SUMIF(C4:C34,"稼働中",H4:H34) | O37: =SUMIF(C4:C34,"稼働中",O4:O34) | P37: =SUMIF(C4:C34,"稼働中",P4:P34) | Q37: =SUMIF(C4:C34,"稼働中",Q4:Q34) | R37: =SUMIF(C4:C34,"稼働中",R4:R34)

Sheet グレイスライン
A1: グレイスライン 契約管理
A2: 請求ルール: 粗利×60% ※全員松野担当・増員なし
A3: ステータス | B3: 氏名 | C3: 参画時期 | D3: 期間 | E3: 案件/上位 | F3: 案件単価 (上位から) | G3: 仕入単価 (下位へ) | H3: 粗利 | I3: GL請求額 (粗利×60%) | J3: 実入り | K3: 支払サイト | L3: 勤怠表フロー | M3: 送付先 To | N3: 送付先 Cc | O3: 木原さん分 | P3: 更新サイクル | Q3: 精算条件 | R3: 備考
A4: 退場済み | B4: 田中みさ | C4: 2025/1 | D4: 2025/3退場 | E4: 相馬さん | F4: 430000 | G4: 400000 | H4: =F4-G4 | L4: 上位からくる | O4: 0 | P4: 3か月更新 | Q4: 固定
A5: 稼働中 | B5: 石崎春光 | C5: 2024/9 | D5: 長期 | E5: スウェル（松崎様） | F5: 680000 | G5: 640000 | H5: =F5-G5 | I5: =H5*0.6 | J5: =I5-O5 | L5: 上位からくる | M5: support_hajimariworks@hajimari.inc | N5: t.matsuzaki@hajimari.inc | O5: 0 | P5: 四半期更新 | Q5: 上下割140-200h | R5: 天王洲アイル
A6: 稼働中 | B6: 山内清 | C6: 2024/10 | D6: 長期 | E6: スウェル | F6: 440000 | G6: 370000 | H6: =F6-G6 | I6: =H6*0.6 | J6: =I6-O6 | L6: 上位からくる | O6: 10000 | P6: 3か月更新 | Q6: 上下割150-190h | R6: 年金機構保守 吉祥寺
A7: 稼働中 | B7: 荒井大輝 | C7: 2025/6 | D7: 長期 | E7: スウェル（テックビズ） | F7: 620000 | G7: 550000 | H7: =F7-G7 | I7: =H7*0.6 | J7: =I7-O7 | L7: 上位からくる | O7: 10000 | P7: 3か月更新 | Q7: 上下割140-200h | R7: Java 赤坂見附
A8: 退場済み | B8: 立野和紀 | C8: 2025/7 | D8: 2025/3退場 | E8: スウェル（エンジニアのミカタ） | F8: 520000 | G8: 450000 | H8: =F8-G8 | L8: 所属から回収 | O8: 10000 | Q8: 固定 | R8: 食品業界 天王町
A9: 退場済み | B9: 吉田 | C9: 2024/7 | D9: 退場済み | E9: システムワークス | F9: 810000 | G9: 760000 | H9: =F9-G9 | L9: 上位からくる | O9: 0 | R9: Java
A10: 退場済み | B10: 高橋 | C10: 2024/8 | D10: 2025/3退場 | E10: Aster | F10: 304000 | G10: 280000 | H10: =F10-G10 | L10: 下からくる | O10: 0 | Q10: 時給1900 | R10: コール
A11: 退場済み | B11: 小松 | C11: 2024/8 | D11: 2025/5退場 | E11: スウェル（テックビズ） | F11: 600000 | G11: 550000 | H11: =F11-G11 | L11: 下からくる | O11: 0 | Q11: 上下割 | R11: C# フルリモ
A12: 退場済み | B12: 佐藤 | C12: 2024/9 | D12: 退場済み | E12: 和田さん | F12: 690000 | G12: 630000 | H12: =F12-G12 | L12: 下からくる | O12: 0 | R12: Nuxt
A13: 退場済み | B13: 木内 | C13: 2025/1 | D13: 2025/3退場 | E13: スウェル | F13: 700000 | G13: 620000 | H13: =F13-G13 | L13: 上位からくる | O13: 0 | Q13: 上下割140-200h | R13: 要件定義 赤坂見附
A14: 退場済み | B14: 染谷 | C14: 2025/2 | D14: 2025/9退場 | E14: スウェル（ブランチ） | F14: 660000 | G14: 570000 | H14: =F14-G14 | L14: 上位からくる | O14: 10000 | Q14: 上下割140-200h | R14: Java 赤坂見附
A15: 退場済み | B15: 女鹿 | C15: 2025/3 | D15: 2025/7退場 | E15: スウェル（工藤さん） | F15: 830000 | G15: 810000 | H15: =F15-G15 | L15: 上位からくる | M15: contact@k-sync.com | O15: 0 | Q15: 上下割140-200h | R15: フロント開発
A16: 退場済み | B16: 井下 | C16: 2025/4 | D16: 2026/2退場 | E16: スウェル（テックビズ） | F16: 740000 | G16: 670000 | H16: =F16-G16 | L16: 上位からくる | O16: 10000 | Q16: 上下割140-200h | R16: iOS 赤坂見附
A17: 退場済み | B17: 筒井 | C17: 2025/6 | D17: 2025/10退場 | E17: スウェル（SEシェア） | F17: 600000 | G17: 530000 | H17: =F17-G17 | L17: 上位からくる | O17: 10000 | Q17: 上下割140-200h | R17: Java 赤坂見附
A18: 退場済み | B18: 守山 | C18: 2025/10 | D18: 2025/12退場 | E18: スウェル（エプコット） | F18: 600000 | G18: 480000 | H18: =F18-G18 | L18: 上位からくる | O18: 0 | Q18: 上下割140-200h | R18: SQL 赤坂見附
A19: 退場済み | B19: 木村（GL） | C19: 2025/10 | D19: 2026/2退場 | E19: スウェル | F19: 670000 | G19: 600000 | H19: =F19-G19 | L19: 上位からくる | O19: 10000 | Q19: 上下割140-200h | R19: Java 赤坂見附
A20: 稼働中合計 | F20: =SUMIF(A4:A19,"稼働中",F4:F19) | H20: =SUMIF(A4:A19,"稼働中",H4:H19) | I20: =SUMIF(A4:A19,"稼働中",I4:I19) | J20: =SUMIF(A4:A19,"稼働中",J4:J19)

Sheet フラップテック
A1: フラップテック 契約管理
A2: 請求ルール: 通常=粗利×68% 小坂折半=粗利×48% 岡本担当=粗利×68%全額払出 岡本折半=粗利×68%の50%払出
A3: 担当 | B3: ステータス | C3: 氏名 | D3: 参画時期 | E3: 期間 | F3: 案件/上位 | G3: 案件単価 (上位から) | H3: 仕入単価 (下位へ) | I3: 粗利 | J3: FT請求額 | K3: 岡本払出 | L3: 実入り | M3: 支払サイト | N3: 勤怠表フロー | O3: 送付先 | P3: 木原さん分 | Q3: 更新サイクル | R3: 備考
B4: 稼働中 | C4: 笠井健太 | D4: 2026/2 | E4: 長期 | F4: スウェル（松堂さん） | G4: 720000 | H4: 620000 | I4: =G4-H4 | J4: =I4*0.68 | L4: =J4 | M4: 45 | N4: 上位からくる | O4: LINE | P4: 10000 | Q4: 四半期更新 | R4: 通信会社運用 門前仲町
B5: 稼働中 | C5: 原昌志 | D5: 2026/3 | E5: スポット | F5: スウェル | G5: 650000 | H5: 550000 | I5: =G5-H5 | J5: =I5*0.68 | L5: =J5 | M5: 45 | N5: 上位からくる | O5: LINE | P5: 20000 | Q5: 単月 | R5: スポット 赤坂見附
B6: 稼働中 | C6: 木村勇太 | D6: 2026/3 | E6: 長期 | F6: スウェル | G6: 670000 | H6: 600000 | I6: =G6-H6 | J6: =I6*0.68 | L6: =J6 | M6: 45 | N6: 上位からくる | O6: LINE | P6: 10000 | Q6: 単月更新 | R6: Java 赤坂見附
A7: 小坂折半 | B7: 稼働中 | C7: 加藤 | D7: 2026/3 | E7: 長期 | F7: スウェル（小坂さん） | G7: 630000 | H7: 550000 | I7: =G7-H7 | J7: =I7*0.48 | L7: =J7 | M7: 45 | N7: 上位からくる | O7: LINE | P7: 11000 | Q7: 四半期更新 | R7: 小坂代表折半→粗利×48%
B8: 稼働中 | C8: 川崎健太 | D8: 2026/4 | E8: 長期 | F8: スウェル | G8: 740000 | H8: 700000 | I8: =G8-H8 | J8: =I8*0.68 | L8: =J8 | M8: 45 | N8: 上位からくる | O8: LINE | P8: 5000 | Q8: 単月更新 | R8: 赤坂見附リモート併用
B9: 稼働中 | C9: 田中みさ | D9: 2026/4 | E9: 長期 | F9: 相馬さん | G9: 430000 | H9: 400000 | I9: =G9-H9 | J9: =I9*0.68 | L9: =J9 | M9: 55 | N9: 上位からくる | O9: LINE | P9: 0 | Q9: 3か月更新 | R9: 固定精算
B10: 稼働中 | C10: 立野和紀 | D10: 2026/4 | E10: 長期 | F10: スウェル（エンジニアのミカタ） | G10: 520000 | H10: 450000 | I10: =G10-H10 | J10: =I10*0.68 | L10: =J10 | M10: 45 | N10: 所属から回収 | P10: 10000 | Q10: 3か月更新 | R10: 食品業界 固定精算
B11: 稼働中 | C11: 佐々木駿 | D11: 2026/4 | E11: 長期 | F11: スウェル | G11: 650000 | H11: 610000 | I11: =G11-H11 | J11: =I11*0.68 | L11: =J11 | M11: 45 | N11: 上位からくる | O11: LINE | P11: 20000 | Q11: 単月更新 | R11: Java 赤坂見附
A12: 岡本折半 | B12: 稼働中 | C12: 橋本奈緒 | D12: 2026/4 | E12: 長期 | F12: スウェル（岡本テラシーク） | G12: 570000 | H12: 500000 | I12: =G12-H12 | J12: =I12*0.68 | K12: =J12*0.5 | L12: =J12-K12 | M12: 45 | N12: 上位からくる | O12: LINE | P12: 10000 | Q12: 単月更新 | R12: 赤坂見附 週3出社
A13: 小坂折半 | B13: 稼働中 | C13: 吉田祥平 | D13: 2026/6 | E13: 長期 | F13: 省庁ネットワーク/ICT運用（FP経由） | G13: 750000 | H13: 700000 | I13: =G13-H13 | J13: =I13*0.48 | L13: =J13 | M13: 45 | N13: 所属からメール | Q13: 単月更新 | R13: 上位→FP→TERRA→所属。FP単価75万、FP-TR間70万。精算条件140-180h中間割4,370円。小坂折半で粗利×48%請求
A14: 岡本 | G14: 720000 | H14: 650000 | I14: =G13-H13 | M14: 45 | O14: LINE | P14: 0 | Q14: 単月更新 | R14: 基幹システム開発 中間割170h 岡本担当→全額払出
A15: 稼働中合計 | G15: =SUMIF(B4:B13,"稼働中",G4:G13) | I15: =SUMIF(B4:B13,"稼働中",I4:I13) | J15: =SUMIF(B4:B13,"稼働中",J4:J13) | K15: =SUMIF(B4:B13,"稼働中",K4:K13) | L15: =SUMIF(B4:B13,"稼働中",L4:L13)

Sheet 月次サマリー
A1: 月次収支サマリー
A2: 対象月:
A3: 区分 | B3: 稼働人数 | C3: 合計売上 (単価合計) | D3: 合計粗利 | E3: 請求額 (実入り) | F3: 岡本 払出合計 | G3: 実入り合計 | H3: 備考
A4: TERRA（プロパー・松野） | E4: =SUMIF(TERRA!C4:C35,"稼働中",TERRA!R4:R35)-SUMIF(TERRA!A4:A35,"岡本",TERRA!R4:R35)
A5: TERRA（プロパー・岡本） | E5: =SUMIF(TERRA!A4:A35,"岡本",TERRA!P4:P35) | F5: =SUMIF(TERRA!A4:A35,"岡本",TERRA!Q4:Q35) | G5: =C4-D4 | H5: 9,000/人払出
A6: TERRA（BP） | E6: =SUMIF(TERRA!B4:B35,"BP",TERRA!P4:P35) | F6: =SUMIF(TERRA!B4:B35,"BP",TERRA!Q4:Q35) | G6: =C5-D5
A7: グレイスライン | E7: =SUMIF(グレイスライン!A4:A19,"稼働中",グレイスライン!J4:J19) | H7: 粗利×60%
A8: フラップテック | E8: =SUMIF(フラップテック!B4:B14,"稼働中",フラップテック!L4:L14) | F8: =SUMIF(フラップテック!B4:B14,"稼働中",フラップテック!K4:K14) | G8: =C7-D7 | H8: 粗利×68%(小坂折半のみ48%) ※FP折半分(上位差益×50%)は別途TERRA列に加算
A9: 合計 | E9: =SUM(C4:C8) | F9: =SUM(D4:D8) | G9: =C9-D9

Sheet 入金予測
A1: 入金予測（5月稼働分〜9月稼働分）
A2: ※TERRA：請求額(税抜)×10.21%を源泉控除 GL/FT：税込がそのまま実入り ※木原さん分は入金後に個人的に渡す
A3: 入金予定日 | B3: 稼働月 | C3: TERRA 請求(税抜) | D3: 源泉徴収 (税抜×10.21%) | E3: TERRA 税込入金 | F3: TERRA 実入り (税込-源泉) | G3: GL 税込 | H3: FT 税込 | I3: 岡本払出 | J3: 木原さん分 (後渡し) | K3: 総実入り
A4: ◆ 2026年6月 入金分
A5: 2026/06/30 | B5: 5月稼働分 | C5: 15000 | D5: 1532 | E5: 16500 | F5: 14968 | G5: 26400 | H5: - | I5: - | J5: - | K5: 41368
A6: 6月 小計 | C6: =SUM(C5:C5) | D6: =SUM(D5:D5) | E6: =SUM(E5:E5) | F6: =SUM(F5:F5) | G6: =SUM(G5:G5) | H6: =SUM(H5:H5) | I6: =SUM(I5:I5) | J6: =SUM(J5:J5) | K6: =SUM(K5:K5)
A7: ◆ 2026年7月 入金分
A8: 2026/07/15 | B8: 5月稼働分 | C8: 412000 | D8: 42065 | E8: 453200 | F8: 411135 | G8: 92400 | H8: 483560 | I8: 100400 | J8: 116000 | K8: 770695
A9: 2026/07/31 | B9: 6月稼働分 | C9: 120000 | D9: 12252 | E9: 132000 | F9: 119748 | G9: 26400 | H9: - | I9: 18000 | J9: - | K9: 128148
A10: 7月 小計 | C10: =SUM(C8:C9) | D10: =SUM(D8:D9) | E10: =SUM(E8:E9) | F10: =SUM(F8:F9) | G10: =SUM(G8:G9) | H10: =SUM(H8:H9) | I10: =SUM(I8:I9) | J10: =SUM(J8:J9) | K10: =SUM(K8:K9)
A11: ◆ 2026年8月 入金分
A12: 2026/08/15 | B12: 6月稼働分 | C12: 428000 | D12: =C12*0.1021 | E12: =C12*1.1 | F12: =E12-D12 | G12: 92400 | H12: 509960 | I12: 100400 | J12: 116000 | K12: =F12+G12+H12-I12-J12
A13: 2026/08/31 | B13: 7月稼働分 | C13: 120000 | D13: 12252 | E13: 132000 | F13: 119748 | G13: 26400 | H13: - | I13: 18000 | J13: - | K13: 128148
A14: 8月 小計 | C14: =SUM(C12:C13) | D14: =SUM(D12:D13) | E14: =SUM(E12:E13) | F14: =SUM(F12:F13) | G14: =SUM(G12:G13) | H14: =SUM(H12:H13) | I14: =SUM(I12:I13) | J14: =SUM(J12:J13) | K14: =SUM(K12:K13)
A15: ◆ 2026年9月 入金分
A16: 2026/09/15 | B16: 7月稼働分 | C16: 428000 | D16: =C16*0.1021 | E16: =C16*1.1 | F16: =E16-D16 | G16: 92400 | H16: 509960 | I16: 100400 | J16: 116000 | K16: =F16+G16+H16-I16-J16
A17: 2026/09/30 | B17: 8月稼働分 | C17: 120000 | D17: 12252 | E17: 132000 | F17: 119748 | G17: 26400 | H17: - | I17: 18000 | J17: - | K17: 128148
A18: 9月 小計 | C18: =SUM(C16:C17) | D18: =SUM(D16:D17) | E18: =SUM(E16:E17) | F18: =SUM(F16:F17) | G18: =SUM(G16:G17) | H18: =SUM(H16:H17) | I18: =SUM(I16:I17) | J18: =SUM(J16:J17) | K18: =SUM(K16:K17)
A19: ◆ 2026年10月 入金分
A20: 2026/10/15 | B20: 8月稼働分 | C20: 428000 | D20: =C20*0.1021 | E20: =C20*1.1 | F20: =E20-D20 | G20: 92400 | H20: 509960 | I20: 100400 | J20: 116000 | K20: =F20+G20+H20-I20-J20
A21: 2026/10/31 | B21: 9月稼働分 | C21: 120000 | D21: 12252 | E21: 132000 | F21: 119748 | G21: 26400 | H21: - | I21: 18000 | J21: - | K21: 128148
A22: 10月 小計 | C22: =SUM(C20:C21) | D22: =SUM(D20:D21) | E22: =SUM(E20:E21) | F22: =SUM(F20:F21) | G22: =SUM(G20:G21) | H22: =SUM(H20:H21) | I22: =SUM(I20:I21) | J22: =SUM(J20:J21) | K22: =SUM(K20:K21)
A23: ◆ 2026年11月 入金分
A24: 2026/11/15 | B24: 9月稼働分 | C24: 428000 | D24: =C24*0.1021 | E24: =C24*1.1 | F24: =E24-D24 | G24: 92400 | H24: 509960 | I24: 100400 | J24: 116000 | K24: =F24+G24+H24-I24-J24
A25: 2026/11/30 | B25: 9月稼働分 | C25: 105000 | D25: 10720 | E25: 115500 | F25: 104780 | G25: - | H25: - | I25: 18000 | J25: - | K25: 86780
A26: 11月 小計 | C26: =SUM(C24:C25) | D26: =SUM(D24:D25) | E26: =SUM(E24:E25) | F26: =SUM(F24:F25) | G26: =SUM(G24:G25) | H26: =SUM(H24:H25) | I26: =SUM(I24:I25) | J26: =SUM(J24:J25) | K26: =SUM(K24:K25)
A28: 総合計（5〜9月稼働分） | C28: =SUM(C4:C26) | D28: =SUM(D4:D26) | E28: =SUM(E4:E26) | F28: =SUM(F4:F26) | G28: =SUM(G4:G26) | H28: =SUM(H4:H26) | I28: =SUM(I4:I26) | J28: =SUM(J4:J26) | K28: =SUM(K4:K26)
A29: ※吉田祥平(2026/6〜): TERRA粗利5万×80%=4万(税抜)+FP粗利5万×48%=2.4万(税込26,400円)。月合計実入り約6.4万円。
